<Properties StartupConfiguration="{5758BF0D-7ECF-4A6C-AF30-1FCC116254DA}|Default">
  <MonoDevelop.Ide.Workbench ActiveDocument="DemoUITest.UITests/Tests/BaseTest.cs">
    <Files>
      <File FileName="DemoUITest.UITests/Tests/BaseTest.cs" Line="1" Column="12" />
    </Files>
  </MonoDevelop.Ide.Workbench>
  <MonoDevelop.Ide.Workspace ActiveConfiguration="Debug" />
  <MonoDevelop.Ide.DebuggingService.Breakpoints>
    <BreakpointStore />
  </MonoDevelop.Ide.DebuggingService.Breakpoints>
  <MonoDevelop.Ide.DebuggingService.PinnedWatches />
  <MonoDevelop.Ide.ItemProperties.DemoUITest.Android PreferredExecutionTarget="Android.192.168.56.101:5555" />
  <MultiItemStartupConfigurations />
  <MonoDevelop.Ide.ItemProperties.DemoUITest.iOS PreferredExecutionTarget="MonoDevelop.IPhone.IPhoneSimulatorTarget.AFD407A6-9827-4607-B730-329BF16F4802" />
</Properties>